odoo10_addon_purchase_order_import_ubl-10.0.2.0.2-nspkg.pth
odoo/addons/purchase_order_import_ubl/README.rst
odoo/addons/purchase_order_import_ubl/__init__.py
odoo/addons/purchase_order_import_ubl/__manifest__.py
odoo/addons/purchase_order_import_ubl/demo/demo_data.xml
odoo/addons/purchase_order_import_ubl/i18n/es.po
odoo/addons/purchase_order_import_ubl/i18n/purchase_order_import_ubl.pot
odoo/addons/purchase_order_import_ubl/static/description/icon.png
odoo/addons/purchase_order_import_ubl/tests/__init__.py
odoo/addons/purchase_order_import_ubl/tests/test_order_response_import.py
odoo/addons/purchase_order_import_ubl/tests/test_ubl_order_import.py
odoo/addons/purchase_order_import_ubl/tests/files/order_response_tmpl.xml
odoo/addons/purchase_order_import_ubl/tests/files/quote-PO00004.pdf
odoo/addons/purchase_order_import_ubl/wizard/__init__.py
odoo/addons/purchase_order_import_ubl/wizard/order_response_import.py
odoo/addons/purchase_order_import_ubl/wizard/purchase_order_import.py
odoo10_addon_purchase_order_import_ubl-10.0.2.0.2.dist-info/METADATA
odoo10_addon_purchase_order_import_ubl-10.0.2.0.2.dist-info/WHEEL
odoo10_addon_purchase_order_import_ubl-10.0.2.0.2.dist-info/namespace_packages.txt
odoo10_addon_purchase_order_import_ubl-10.0.2.0.2.dist-info/top_level.txt
odoo10_addon_purchase_order_import_ubl-10.0.2.0.2.dist-info/RECORD
